rishtedaar/__init__.py
rishtedaar/apps.py
rishtedaar/urls.py
rishtedaar/views.py
rishtedaar/checks/__init__.py
rishtedaar/checks/cache_check.py
rishtedaar/checks/celery_check.py
rishtedaar/checks/db_check.py
rishtedaar/checks/health_check.py
rishtedaar/checks/rmq_check.py
rishtedaar-1.0.6.dist-info/LICENSE
rishtedaar-1.0.6.dist-info/METADATA
rishtedaar-1.0.6.dist-info/WHEEL
rishtedaar-1.0.6.dist-info/top_level.txt
rishtedaar-1.0.6.dist-info/RECORD
